src/test/ffe_tap.v
`timescale 1ns / 1ps 

module ffe_tap ( 
    input  wire               clk,
    input  wire               rst_n, 
    input  wire               enable_adapt, // HIGH to enable SS-LMS
    input  wire signed [7:0]  rx_data,      // 8-bit quantized data from ADC 
    input  wire signed [15:0] error_val,    // Signed error from slicer 
    output wire signed [15:0] tap_out       // Product of data and top 8 bits of coefficients 
); 

    // 16-bit accumulator: [15:8] is integer, [7:0] is fractional
    reg signed [15:0] coef_acc; 

    // Slice off top 8 bits of accumulator to use as filter weight
    wire signed [7:0] active_weight = coef_acc[15:8]; 

    // 8-bit data * 8-bit weight = 16-bit output 
    assign tap_out = rx_data * active_weight; 

    // Extract sign bits (MSB in 2's complement)
    wire data_sign  = rx_data[7];
    wire error_sign = error_val[15];

    // SS-LMS logic 
    always @(posedge clk or negedge rst_n) begin 
        if (!rst_n) begin 
            // Initialize coeff accumulator to 1.0 in 8.8 fixed point (0x0100)
            coef_acc <= 16'h0100;
        end else if (enable_adapt) begin
            // Sign match = product of sign is (+) = subtract 1 LSB from accumulator
            // Sign mismatch = product of sign is (-) = add 1 LSB to accumulator
            if (data_sign == error_sign) begin 
                coef_acc <= coef_acc - 16'd1;
            end else begin 
                coef_acc <= coef_acc + 16'd1;
            end 
        end
    end 
    
endmodule

src/test/ffe_tap_tb.v
`timescale 1ns / 1ps

module ffe_tap_tb;

    // Inputs to the Device Under Test (DUT)
    reg         clk;
    reg         rst_n;
    reg         enable_adapt;
    reg  [7:0]  rx_data;
    reg  [15:0] error_val;

    // Outputs from the DUT
    wire [15:0] tap_out;

    // Instantiate the Device Under Test
    ffe_tap u_ffe_tap (
        .clk(clk),
        .rst_n(rst_n),
        .enable_adapt(enable_adapt),
        .rx_data(rx_data),
        .error_val(error_val),
        .tap_out(tap_out)
    );

    // 1. Clock Generation (50MHz for easy viewing)
    always #10 clk = ~clk;

    initial begin
        // Initialize signals
        clk = 0;
        rst_n = 0;
        enable_adapt = 0;
        rx_data = 8'd0;
        error_val = 16'd0;

        // Setup waveform dumping for GTKWave
        $dumpfile("ffe_tap_wave.vcd");
        $dumpvars(0, ffe_tap_tb);

        // 2. Apply Reset
        #25;
        rst_n = 1; // Release reset
        #20;
        
        // 3. Test Case 1: Enable adaptation, apply MATCHING signs
        // Both rx_data and error_val are positive (Sign bits = 0)
        // Expectation: Accumulator should subtract 1 LSB every clock edge
        $display("--- Test Case 1: Matching Positive Signs ---");
        enable_adapt = 1;
        rx_data   = 8'sb0000_1010;   // +10
        error_val = 16'sb0000_0000_0000_0101; // +5
        #40; // Let it run for 2 clock cycles

        // 4. Test Case 2: Apply MISMATCHING signs
        // rx_data is positive (0), error_val is negative (1)
        // Expectation: Accumulator should add 1 LSB every clock edge
        $display("--- Test Case 2: Mismatching Signs ---");
        rx_data   = 8'sb0000_1010;   // +10 (Positive)
        error_val = 16'sb1000_0000_0000_0101; // Negative
        #40; // Let it run for 2 clock cycles

        // 5. Test Case 3: Disable adaptation
        // Expectation: Accumulator frozen, output remains completely static
        $display("--- Test Case 3: Disable Adaptation ---");
        enable_adapt = 0;
        rx_data   = 8'sb0000_0001;   // Change data to check multiplier
        #40;

        $display("Simulation complete.");
        $finish;
    end

endmodule

src/test/ffe_tap_wave.vcd
$date
	Mon Jun 15 16:27:19 2026
$end
$version
	Icarus Verilog
$end
$timescale
	1ps
$end
$scope module ffe_tap_tb $end
$var wire 16 ! tap_out [15:0] $end
$var reg 1 " clk $end
$var reg 1 # enable_adapt $end
$var reg 16 $ error_val [15:0] $end
$var reg 1 % rst_n $end
$var reg 8 & rx_data [7:0] $end
$scope module u_ffe_tap $end
$var wire 1 " clk $end
$var wire 1 # enable_adapt $end
$var wire 16 ' error_val [15:0] $end
$var wire 1 % rst_n $end
$var wire 8 ( rx_data [7:0] $end
$var wire 16 ) tap_out [15:0] $end
$var wire 1 * error_sign $end
$var wire 1 + data_sign $end
$var wire 8 , active_weight [7:0] $end
$var reg 16 - coef_acc [15:0] $end
$upscope $end
$upscope $end
$enddefinitions $end
$comment Show the parameter values. $end
$dumpall
$end
#0
$dumpvars
b100000000 -
b1 ,
0+
0*
b0 )
b0 (
b0 '
b0 &
0%
b0 $
0#
0"
b0 !
$end
#10000
1"
#20000
0"
#25000
1%
#30000
1"
#40000
0"
#45000
b101 $
b101 '
b1010 !
b1010 )
b1010 &
b1010 (
1#
#50000
b0 !
b0 )
b0 ,
b11111111 -
1"
#60000
0"
#70000
b11111110 -
1"
#80000
0"
#85000
1*
b1000000000000101 $
b1000000000000101 '
#90000
b11111111 -
1"
#100000
0"
#110000
b1010 !
b1010 )
b1 ,
b100000000 -
1"
#120000
0"
#125000
b1 !
b1 )
b1 &
b1 (
0#
