src/Equalizer/dfe_tap.v
`timescale 1ps/1ps

module dfe_tap (
    input  wire               clk,
    input  wire               rst_n,
    input  wire               enable_adapt,      // HIGH to enable adaptation
    input  wire signed [15:0] error_val,         // 16-bit signed error from top level
    input  wire        [1:0]  prev_decision_code,// 2-bit decision code from previous cycle
    input  wire signed [15:0] prev_ideal_target, // Previous cycle's noiseless target voltage
    output wire signed [17:0] dfe_out            // 18-bit feedback correction signal
);

reg signed [15:0] dfe_acc; // 16-bit accumulator, [15:8] is integer weight, [7:0] is fractional

wire signed [7:0] active_dfe_weight = dfe_acc[15:8]; // extract first 8 bits as active integer weight

// LMS sign extraction 
wire error_sign = error_val[15];
// sign of previous decision 
// given 2'b11 (+3) and 2'b10 (+1) are positive, 2'b01 (-1) and 2'b00 (-3) are negative
// --> MSB of decision code directly represents sign 
wire prev_sign = prev_decision_code[1];

// sequential weight update 
always @(posedge clk or negedge rst_n) begin
    if (!rst_n) begin
        //initialize DFE weight to 0.0
        dfe_acc <= 16'sh0000;
    end
    else if(enable_adapt) begin
        // SS-LMS for DFE
        // if sign matches (+/+, -/-), product is (+) -> add 1 LSB to cancel ISI
        // is sign mismatch (+/-), product is (-) -> subtract 1 LSB 
        if (error_sign == prev_sign) begin
            dfe_acc <= dfe_acc + 16'sd1;
        end else begin 
            dfe_acc <= dfe_acc - 16'sd1;
        end
    end
end

// combinational multiplication
// 8-bit weight * 16-bit target = 24-bit raw signed product 
wire signed [23:0] dfe_out_full = active_dfe_weight * prev_ideal_target;

// slice bottom 18 bits to match top level FFE adder tree
assign dfe_out = dfe_out_full[17:0];

endmodule

src/Equalizer/pam4_slicer.v
`timescale 1ps/1ps

module pam4_slicer (
    input wire signed [17:0] eq_signal, // from FFE adder tree
    output reg [1:0] decision_code, // 2-bit digital representation from PAM4 symbol
    output reg signed [15:0] ideal_target // noiseless ref. volage in ADC LSB
);

    // define the slicing thresholds based on 31 LSBs/Volt
    localparam signed [17:0] TH_POS  = 18'sd62;   //  2.0 Volts
    localparam signed [17:0] TH_ZERO = 18'sd0;    //  0.0 Volts
    localparam signed [17:0] TH_NEG  = -18'sd62;  // -2.0 Volts

    // define ideal noiseless target output code
    localparam signed [15:0] REF_P3  = 16'sd93;   //  3.0 Volts
    localparam signed [15:0] REF_P1  = 16'sd31;   //  1.0 Volts
    localparam signed [15:0] REF_N1  = -16'sd31;  // -1.0 Volts
    localparam signed [15:0] REF_N3  = -16'sd93;  // -3.0 Volts

    // Combinational evaluation block
    always @(*) begin
        if (eq_signal >= TH_POS) begin
            decision_code = 2'b11;  // Represents +3
            ideal_target  = REF_P3;
        end 
        else if (eq_signal >= TH_ZERO && eq_signal < TH_POS) begin
            decision_code = 2'b10;  // Represents +1
            ideal_target  = REF_P1;
        end 
        else if (eq_signal >= TH_NEG && eq_signal < TH_ZERO) begin
            decision_code = 2'b01;  // Represents -1
            ideal_target  = REF_N1;
        end 
        else begin
            decision_code = 2'b00;  // Represents -3
            ideal_target  = REF_N3;
        end
    end
endmodule

src/test/ffe_tap.v
`timescale 1ns / 1ps 

module ffe_tap ( 
    input  wire               clk,
    input  wire               rst_n, 
    input  wire               enable_adapt, // HIGH to enable SS-LMS
    input  wire signed [7:0]  rx_data,      // 8-bit quantized data from ADC 
    input  wire signed [15:0] error_val,    // Signed error from slicer 
    output wire signed [15:0] tap_out       // Product of data and top 8 bits of coefficients 
); 

    // 16-bit accumulator: [15:8] is integer, [7:0] is fractional
    reg signed [15:0] coef_acc; 

    // Slice off top 8 bits of accumulator to use as filter weight
    wire signed [7:0] active_weight = coef_acc[15:8]; 

    // 8-bit data * 8-bit weight = 16-bit output 
    assign tap_out = rx_data * active_weight; 

    // Extract sign bits (MSB in 2's complement)
    wire data_sign  = rx_data[7];
    wire error_sign = error_val[15];

    // SS-LMS logic 
    always @(posedge clk or negedge rst_n) begin 
        if (!rst_n) begin 
            // Initialize coeff accumulator to 1.0 in 8.8 fixed point (0x0100)
            coef_acc <= 16'h0100;
        end else if (enable_adapt) begin
            // Sign match = product of sign is (+) = subtract 1 LSB from accumulator
            // Sign mismatch = product of sign is (-) = add 1 LSB to accumulator
            if (data_sign == error_sign) begin 
                coef_acc <= coef_acc - 16'd1;
            end else begin 
                coef_acc <= coef_acc + 16'd1;
            end 
        end
    end 
    
endmodule

src/Equalizer/equalizer_top.v
`timescale 1ps/1ps

module equalizer_top (
    input wire clk, 
    input wire rst_n,
    input wire enable_adapt,
    input wire signed [7:0] rx_data,
    output wire signed [15:0] eq_output
);

// FFE delay line
// holding 2 previous 8-bit samples for 3-tap FFE
reg signed [7:0] rx_data_d1;
reg signed [7:0] rx_data_d2;

always @(posedge clk or negedge rst_n) begin
    if(!rst_n) begin
        //clear taps on reset 
        rx_data_d1 <= 8'sd0;
        rx_data_d2 <= 8'sd0;
    end else begin
        // shift samples down the taps 
        rx_data_d1 <= rx_data;
        rx_data_d2 <= rx_data_d1;
    end
end

// instantiate 3 FFE taps
wire signed [15:0] tap0_out;
wire signed [15:0] tap1_out;
wire signed [15:0] tap2_out;

wire signed [15:0] error_val; // feedback wire for slicer

    // FFE tap 0
    ffe_tap u_ffe_tap0 (
        .clk (clk),
        .rst_n (rst_n),
        .enable_adapt (enable_adapt),
        .rx_data (rx_data),       // Current sample
        .error_val (error_val),     // Shared feedback error wire
        .tap_out (tap0_out)
    );
    // FFE tap 1
    ffe_tap u_ffe_tap1 (
        .clk (clk),
        .rst_n (rst_n),
        .enable_adapt (enable_adapt),
        .rx_data (rx_data_d1),    // 1-cycle old sample
        .error_val (error_val),
        .tap_out (tap1_out)
    );
    // FFE tap 2
    ffe_tap u_ffe_tap2 (
        .clk (clk),
        .rst_n (rst_n),
        .enable_adapt (enable_adapt),
        .rx_data (rx_data_d2),    // 2-cycles old sample
        .error_val (error_val),
        .tap_out(tap2_out)
    );

   wire signed [17:0] ffe_out; // 18 bits to prevent overflow
   assign ffe_out = tap0_out + tap1_out + tap2_out; // summation

    // DFE loop subtraction 
    wire signed [17:0] dfe_out;
    wire signed [17:0] eq_signal; 

    // equalized signal = FFE output - DFE feedback
    assign eq_signal = ffe_out - dfe_out;

    // connect top level pin
    assign eq_output = eq_signal[15:0];

    // PAM4 slicer
    wire [1:0] decision_code;
    wire signed [15:0] ideal_target;

    pam4_slicer u_slicer (
        .eq_signal (eq_signal),
        .decision_code (decision_code),
        .ideal_target (ideal_target)
    );

    // error calculation for LMS 
    // error = acqual equalized signal - ideal target signal
    // first sign extend ideal_target from 16 to 18 bits to match 
    wire signed [17:0] raw_error = eq_signal - {{2{ideal_target[15]}}, ideal_target};

    //squeeze error val into 16 bits
    assign error_val = raw_error[15:0];

    // DFE pipeline
    // need to capture previous decision --> capture slicer output in registers
    reg [1:0] prev_decision_code;
    reg signed [15:0] prev_ideal_target;

    always @(posedge clk or negedge rst_n) begin
        if (!rst_n) begin
            prev_decision_code <= 2'b10; // default to neutral postive (+1)
            prev_ideal_target <= 16'sd0;
        end else begin 
            prev_decision_code <= decision_code;
            prev_ideal_target <= ideal_target;
        end
    end

    // instantiate DFE module 
    dfe_tap u_dfe_tap (
        .clk (clk),
        .rst_n (rst_n),
        .enable_adapt (enable_adapt),
        .error_val (error_val),
        .prev_decision_code (prev_decision_code),
        .prev_ideal_target (prev_ideal_target),
        .dfe_out (dfe_out)
    );


endmodule

src/Equalizer/tb_equalizer.v
`timescale 1ps/1ps

module tb_equalizer;
    parameter NUM_SAMPLES = 5000; // Matching your MATLAB config
    parameter CLK_PERIOD  = 10;   // 10ns cycle time

    // inputs to DUT
    reg clk;
    reg rst_n;
    reg enable_adapt;
    reg signed [7:0] rx_data;

    // outputs from DUT 
    wire signed [15:0] eq_output;

    // testbench internal memory for MATLAB stimuli
    reg [7:0] rx_mem [0:NUM_SAMPLES - 1];
    integer out_file;
    integer i;

    // instantiate top-level module 
    equalizer_top u_dut (
        .clk(clk),
        .rst_n(rst_n),
        .enable_adapt(enable_adapt),
        .rx_data(rx_data),
        .eq_output(eq_output)
    );

    // clock gen
    initial begin
        clk = 0;
        forever #(CLK_PERIOD / 2) clk = ~clk; // 50% duty cycle
    end

    // for dumping to GTKWave
    initial begin
        $dumpfile("equalizer_sim.vcd"); // Creates the waveform file
        $dumpvars(0, tb_equalizer);     // Dumps ALL signals in the testbench and DUT
    end

    // main co-simulation flow 
    initial begin
        // 1. read MATLAB .hex dump
        $readmemh("rx_stimulus.hex", rx_mem);

        // 2. open output file to dump output
        out_file = $fopen("eq_output_dump.hex", "w");

        // 3. initial reset state 
        rst_n = 0;
        enable_adapt = 0; // keep off to check static behavior 
        rx_data = 8'sd0;

        #(CLK_PERIOD * 5);
        @(negedge clk);
        rst_n = 1; // release reset

        #(CLK_PERIOD * 5);

        // 4. feed stimuli 
        $display(" ----- starting RTL co-sim -----");
        for(i = 0; i < NUM_SAMPLES; i = i + 1) begin
            rx_data = rx_mem[i];

            @(posedge clk); // sample occurs on clk edge

            // log output to file 
            $fdisplay(out_file, "%h", eq_output);

            // turning adaptation on
            if (i == 500) begin 
                $display("Enabling adaptation loop at sample %d", i);
                enable_adapt = 1;
            end 
        end

        // 5. wrap up
        #(CLK_PERIOD * 10);
        $fclose(out_file);
        $display("----- co-sim complete -----");
        $finish;
    end
    
endmodule

src/Equalizer/equalizer_sim.vcd
$date
	Sun Jul  5 22:21:36 2026
$end
$version
	Icarus Verilog
$end
$timescale
	1ps
$end
$scope module tb_equalizer $end
$var wire 16 ! eq_output [15:0] $end
$var parameter 32 " CLK_PERIOD $end
$var parameter 32 # NUM_SAMPLES $end
$var reg 1 $ clk $end
$var reg 1 % enable_adapt $end
$var reg 1 & rst_n $end
$var reg 8 ' rx_data [7:0] $end
$var integer 32 ( i [31:0] $end
$var integer 32 ) out_file [31:0] $end
$scope module u_dut $end
$var wire 1 $ clk $end
$var wire 1 % enable_adapt $end
$var wire 1 & rst_n $end
$var wire 8 * rx_data [7:0] $end
$var wire 16 + tap2_out [15:0] $end
$var wire 16 , tap1_out [15:0] $end
$var wire 16 - tap0_out [15:0] $end
$var wire 18 . raw_error [17:0] $end
$var wire 16 / ideal_target [15:0] $end
$var wire 18 0 ffe_out [17:0] $end
$var wire 16 1 error_val [15:0] $end
$var wire 18 2 eq_signal [17:0] $end
$var wire 16 3 eq_output [15:0] $end
$var wire 18 4 dfe_out [17:0] $end
$var wire 2 5 decision_code [1:0] $end
$var reg 2 6 prev_decision_code [1:0] $end
$var reg 16 7 prev_ideal_target [15:0] $end
$var reg 8 8 rx_data_d1 [7:0] $end
$var reg 8 9 rx_data_d2 [7:0] $end
$scope module u_dfe_tap $end
$var wire 1 $ clk $end
$var wire 1 % enable_adapt $end
$var wire 16 : error_val [15:0] $end
$var wire 2 ; prev_decision_code [1:0] $end
$var wire 16 < prev_ideal_target [15:0] $end
$var wire 1 & rst_n $end
$var wire 1 = prev_sign $end
$var wire 1 > error_sign $end
$var wire 24 ? dfe_out_full [23:0] $end
$var wire 18 @ dfe_out [17:0] $end
$var wire 8 A active_dfe_weight [7:0] $end
$var reg 16 B dfe_acc [15:0] $end
$upscope $end
$scope module u_ffe_tap0 $end
$var wire 1 $ clk $end
$var wire 1 % enable_adapt $end
$var wire 16 C error_val [15:0] $end
$var wire 1 & rst_n $end
$var wire 8 D rx_data [7:0] $end
$var wire 16 E tap_out [15:0] $end
$var wire 1 F error_sign $end
$var wire 1 G data_sign $end
$var wire 8 H active_weight [7:0] $end
$var reg 16 I coef_acc [15:0] $end
$upscope $end
$scope module u_ffe_tap1 $end
$var wire 1 $ clk $end
$var wire 1 % enable_adapt $end
$var wire 16 J error_val [15:0] $end
$var wire 1 & rst_n $end
$var wire 8 K rx_data [7:0] $end
$var wire 16 L tap_out [15:0] $end
$var wire 1 M error_sign $end
$var wire 1 N data_sign $end
$var wire 8 O active_weight [7:0] $end
$var reg 16 P coef_acc [15:0] $end
$upscope $end
$scope module u_ffe_tap2 $end
$var wire 1 $ clk $end
$var wire 1 % enable_adapt $end
$var wire 16 Q error_val [15:0] $end
$var wire 1 & rst_n $end
$var wire 8 R rx_data [7:0] $end
$var wire 16 S tap_out [15:0] $end
$var wire 1 T error_sign $end
$var wire 1 U data_sign $end
$var wire 8 V active_weight [7:0] $end
$var reg 16 W coef_acc [15:0] $end
$upscope $end
$scope module u_slicer $end
$var wire 18 X eq_signal [17:0] $end
$var parameter 16 Y REF_N1 $end
$var parameter 16 Z REF_N3 $end
$var parameter 16 [ REF_P1 $end
$var parameter 16 \ REF_P3 $end
$var parameter 18 ] TH_NEG $end
$var parameter 18 ^ TH_POS $end
$var parameter 18 _ TH_ZERO $end
$var reg 2 ` decision_code [1:0] $end
$var reg 16 a ideal_target [15:0] $end
$upscope $end
$upscope $end
$upscope $end
$enddefinitions $end
$comment Show the parameter values. $end
$dumpall
b0 _
b111110 ^
b111111111111000010 ]
b1011101 \
b11111 [
b1111111110100011 Z
b1111111111100001 Y
b1001110001000 #
b1010 "
$end
#0
$dumpvars
b11111 a
b10 `
b0 X
b100000000 W
b1 V
0U
1T
b0 S
b0 R
b1111111111100001 Q
b100000000 P
b1 O
0N
1M
b0 L
b0 K
b1111111111100001 J
b100000000 I
b1 H
0G
1F
b0 E
b0 D
b1111111111100001 C
b0 B
b0 A
b0 @
b0 ?
1>
1=
b0 <
b10 ;
b1111111111100001 :
b0 9
b0 8
b0 7
b10 6
b10 5
b0 4
b0 3
b0 2
b1111111111100001 1
b0 0
b11111 /
b111111111111100001 .
b0 -
b0 ,
b0 +
b0 *
b10000000000000000000000000000011 )
bx (
b0 '
0&
0%
0$
b0 !
$end
#5
1$
#10
0$
#15
1$
#20
0$
#25
1$
#30
0$
#35
1$
#40
0$
#45
1$
#50
1&
0$
#55
b11111 7
b11111 <
1$
#60
0$
#65
1$
#70
0$
#75
1$
#80
0$
#85
1$
#90
0$
#95
1$
#100
0>
0F
0M
0T
b1111111111100111 !
b1111111111100111 3
b110 1
b110 :
b110 C
b110 J
b110 Q
b1111111111100001 /
b1111111111100001 a
b1 5
b1 `
1G
0$
b110 .
b111111111111100111 2
b111111111111100111 X
b111111111111100111 0
b1111111111100111 -
b1111111111100111 E
b11100111 '
b11100111 *
b11100111 D
b0 (
#105
0=
b1111111111100001 7
b1111111111100001 <
b1 6
b1 ;
b1000001 ,
b1000001 L
b1000001 8
b1000001 K
0>
0F
0M
0T
b10000010 !
b10000010 3
b100101 1
b100101 :
b100101 C
b100101 J
b100101 Q
b1011101 /
b1011101 a
b11 5
b11 `
0G
b100101 .
b10000010 2
b10000010 X
b10000010 0
b1000001 -
b1000001 E
b1000001 '
b1000001 *
b1000001 D
b1 (
1$
#110
0$
#115
1=
b1000001 +
b1000001 S
b1000001 9
b1000001 R
b110010 ,
b110010 L
b110010 8
b110010 K
b1011101 7
b1011101 <
b11 6
b11 ;
b10100101 !
b10100101 3
b1001000 1
b1001000 :
b1001000 C
b1001000 J
b1001000 Q
b1001000 .
b10100101 2
b10100101 X
b10100101 0
b110010 -
b110010 E
b110010 '
b110010 *
b110010 D
b10 (
1$
#120
0$
#125
b110010 +
b110010 S
b110010 9
b110010 R
b101011 ,
b101011 L
b101011 8
b101011 K
b10001000 !
b10001000 3
b101011 1
b101011 :
b101011 C
b101011 J
b101011 Q
b101011 .
b10001000 2
b10001000 X
b10001000 0
b101011 -
b101011 E
b101011 '
b101011 *
b101011 D
b11 (
1$
#130
0$
#135
1N
b101011 +
b101011 S
b101011 9
b101011 R
b1111111111000010 ,
b1111111111000010 L
b11000010 8
b11000010 K
0>
0F
0M
0T
b1111111110101111 !
b1111111110101111 3
b1100 1
b1100 :
b1100 C
b1100 J
b1100 Q
b1111111110100011 /
b1111111110100011 a
b0 5
b0 `
1G
b1100 .
b111111111110101111 2
b111111111110101111 X
b111111111110101111 0
b1111111111000010 -
b1111111111000010 E
b11000010 '
b11000010 *
b11000010 D
b100 (
1$
#140
0$
#145
0=
1U
b1111111110100011 7
b1111111110100011 <
b0 6
b0 ;
b1111111111000010 +
b1111111111000010 S
b11000010 9
b11000010 R
b1111111110011101 ,
b1111111110011101 L
b10011101 8
b10011101 K
1>
1F
1M
1T
b1111111011111100 !
b1111111011111100 3
b1111111101011001 1
b1111111101011001 :
b1111111101011001 C
b1111111101011001 J
b1111111101011001 Q
b111111111101011001 .
b111111111011111100 2
b111111111011111100 X
b111111111011111100 0
b1111111110011101 -
b1111111110011101 E
b10011101 '
b10011101 *
b10011101 D
b101 (
1$
#150
0$
#155
b1111111110011101 +
b1111111110011101 S
b10011101 9
b10011101 R
b1111111110010000 ,
b1111111110010000 L
b10010000 8
b10010000 K
b1111111010111101 !
b1111111010111101 3
b1111111100011010 1
b1111111100011010 :
b1111111100011010 C
b1111111100011010 J
b1111111100011010 Q
b111111111100011010 .
b111111111010111101 2
b111111111010111101 X
b111111111010111101 0
b1111111110010000 -
b1111111110010000 E
b10010000 '
b10010000 *
b10010000 D
b110 (
1$
#160
0$
#165
1>
1F
1M
1T
b1111111111100001 /
b1111111111100001 a
b1 5
b1 `
0N
b1111111110010000 +
b1111111110010000 S
b10010000 9
b10010000 R
b100101 ,
b100101 L
b100101 8
b100101 K
b1111111111011010 !
b1111111111011010 3
b1111111111111001 1
b1111111111111001 :
b1111111111111001 C
b1111111111111001 J
b1111111111111001 Q
0G
b111111111111111001 .
b111111111111011010 2
b111111111111011010 X
b111111111111011010 0
b100101 -
b100101 E
b100101 '
b100101 *
b100101 D
b111 (
1$
#170
0$
#175
0>
0F
0M
0T
0U
b1011101 /
b1011101 a
b11 5
b11 `
b100101 +
b100101 S
b100101 9
b100101 R
b101011 ,
b101011 L
b101011 8
b101011 K
b1111111111100001 7
b1111111111100001 <
b1 6
b1 ;
b1111011 !
b1111011 3
b11110 1
b11110 :
b11110 C
b11110 J
b11110 Q
b11110 .
b1111011 2
b1111011 X
b1111011 0
b101011 -
b101011 E
b101011 '
b101011 *
b101011 D
b1000 (
1$
#180
0$
#185
1=
b10000001 !
b10000001 3
b100100 1
b100100 :
b100100 C
b100100 J
b100100 Q
b1011101 7
b1011101 <
b11 6
b11 ;
b100100 .
b10000001 2
b10000001 X
b10000001 0
b101011 +
b101011 S
b101011 9
b101011 R
b1001 (
1$
#190
0$
#195
1N
b1111111111000010 ,
b1111111111000010 L
b11000010 8
b11000010 K
0>
0F
0M
0T
b1111111110101111 !
b1111111110101111 3
b1100 1
b1100 :
b1100 C
b1100 J
b1100 Q
b1111111110100011 /
b1111111110100011 a
b0 5
b0 `
1G
b1100 .
b111111111110101111 2
b111111111110101111 X
b111111111110101111 0
b1111111111000010 -
b1111111111000010 E
b11000010 '
b11000010 *
b11000010 D
b1010 (
1$
#200
0$
#205
0=
1U
0N
b1111111110100011 7
b1111111110100011 <
b0 6
b0 ;
b1111111111000010 +
b1111111111000010 S
b11000010 9
b11000010 R
b110010 ,
b110010 L
b110010 8
b110010 K
b100110 !
b100110 3
b111 1
b111 :
b111 C
b111 J
b111 Q
b11111 /
b11111 a
b10 5
b10 `
0G
b111 .
b100110 2
b100110 X
b100110 0
b110010 -
b110010 E
b110010 '
b110010 *
b110010 D
b1011 (
1$
#210
0$
#215
0U
1=
b110010 +
b110010 S
b110010 9
b110010 R
b1011101 ,
b1011101 L
b1011101 8
b1011101 K
b11111 7
b11111 <
b10 6
b10 ;
0>
0F
0M
0T
b11101100 !
b11101100 3
b10001111 1
b10001111 :
b10001111 C
b10001111 J
b10001111 Q
b1011101 /
b1011101 a
b11 5
b11 `
b10001111 .
b11101100 2
b11101100 X
b11101100 0
b1011101 -
b1011101 E
b1011101 '
b1011101 *
b1011101 D
b1100 (
1$
#220
0$
#225
1>
1F
1M
1T
b11111 /
b11111 a
b10 5
b10 `
1N
b1011101 7
b1011101 <
b11 6
b11 ;
b1011101 +
b1011101 S
b1011101 9
b1011101 R
b1111111111011011 ,
b1111111111011011 L
b11011011 8
b11011011 K
b10011 !
b10011 3
b1111111111110100 1
b1111111111110100 :
b1111111111110100 C
b1111111111110100 J
b1111111111110100 Q
1G
b111111111111110100 .
b10011 2
b10011 X
b10011 0
b1111111111011011 -
b1111111111011011 E
b11011011 '
b11011011 *
b11011011 D
b1101 (
1$
#230
0$
#235
1U
b1111111111011011 +
b1111111111011011 S
b11011011 9
b11011011 R
b1111111110100011 ,
b1111111110100011 L
b10100011 8
b10100011 K
b11111 7
b11111 <
b10 6
b10 ;
b1111111100100001 !
b1111111100100001 3
b1111111101111110 1
b1111111101111110 :
b1111111101111110 C
b1111111101111110 J
b1111111101111110 Q
b1111111110100011 /
b1111111110100011 a
b0 5
b0 `
b111111111101111110 .
b111111111100100001 2
b111111111100100001 X
b111111111100100001 0
b1111111110100011 -
b1111111110100011 E
b10100011 '
b10100011 *
b10100011 D
b1110 (
1$
#240
0$
#245
0=
b1111111110100011 7
b1111111110100011 <
b0 6
b0 ;
b1111111110100011 +
b1111111110100011 S
b10100011 9
b10100011 R
b1111111110010000 ,
b1111111110010000 L
b10010000 8
b10010000 K
b1111111011000011 !
b1111111011000011 3
b1111111100100000 1
b1111111100100000 :
b1111111100100000 C
b1111111100100000 J
b1111111100100000 Q
b111111111100100000 .
b111111111011000011 2
b111111111011000011 X
b111111111011000011 0
b1111111110010000 -
b1111111110010000 E
b10010000 '
b10010000 *
b10010000 D
b1111 (
1$
#250
0$
#255
b1111111110010000 +
b1111111110010000 S
b10010000 9
b10010000 R
b1111111111000010 ,
b1111111111000010 L
b11000010 8
b11000010 K
b1111111100010100 !
b1111111100010100 3
b1111111101110001 1
b1111111101110001 :
b1111111101110001 C
b1111111101110001 J
b1111111101110001 Q
b111111111101110001 .
b111111111100010100 2
b111111111100010100 X
b111111111100010100 0
b1111111111000010 -
b1111111111000010 E
b11000010 '
b11000010 *
b11000010 D
b10000 (
1$
#260
0$
#265
1>
1F
1M
1T
b1111111111100001 /
b1111111111100001 a
b1 5
b1 `
0N
b1111111111000010 +
b1111111111000010 S
b11000010 9
b11000010 R
b110 ,
b110 L
b110 8
b110 K
b1111111111001110 !
b1111111111001110 3
b1111111111101101 1
b1111111111101101 :
b1111111111101101 C
b1111111111101101 J
b1111111111101101 Q
0G
b111111111111101101 .
b111111111111001110 2
b111111111111001110 X
b111111111111001110 0
b110 -
b110 E
b110 '
b110 *
b110 D
b10001 (
1$
#270
0$
#275
0U
1N
b110 +
b110 S
b110 9
b110 R
b1111111111101101 ,
b1111111111101101 L
b11101101 8
b11101101 K
b1111111111100001 7
b1111111111100001 <
b1 6
b1 ;
1>
1F
1M
1T
b1111111111100000 !
b1111111111100000 3
b1111111111111111 1
b1111111111111111 :
b1111111111111111 C
b1111111111111111 J
b1111111111111111 Q
b1111111111100001 /
b1111111111100001 a
b1 5
b1 `
1G
b111111111111111111 .
b111111111111100000 2
b111111111111100000 X
b111111111111100000 0
b1111111111101101 -
b1111111111101101 E
b11101101 '
b11101101 *
b11101101 D
b10010 (
1$
#280
0$
#285
0>
0F
0M
0T
1U
b1111111110100011 /
b1111111110100011 a
b0 5
b0 `
b1111111111101101 +
b1111111111101101 S
b11101101 9
b11101101 R
b1111111111100001 ,
b1111111111100001 L
b11100001 8
b11100001 K
b1111111110101111 !
b1111111110101111 3
b1100 1
b1100 :
b1100 C
b1100 J
b1100 Q
b1100 .
b111111111110101111 2
b111111111110101111 X
b111111111110101111 0
b1111111111100001 -
b1111111111100001 E
b11100001 '
b11100001 *
b11100001 D
b10011 (
1$
#290
0$
#295
0N
b1111111111100001 +
b1111111111100001 S
b11100001 9
b11100001 R
b1100 ,
b1100 L
b1100 8
b1100 K
b1111111110100011 7
b1111111110100011 <
b0 6
b0 ;
0>
0F
0M
0T
b1111111111111001 !
b1111111111111001 3
b11000 1
b11000 :
b11000 C
b11000 J
b11000 Q
b1111111111100001 /
b1111111111100001 a
b1 5
b1 `
0G
b11000 .
b111111111111111001 2
b111111111111111001 X
b111111111111111001 0
b1100 -
b1100 E
b1100 '
b1100 *
b1100 D
b10100 (
1$
#300
0$
#305
0U
1N
b1111111111100001 7
b1111111111100001 <
b1 6
b1 ;
b1100 +
b1100 S
b1100 9
b1100 R
b1111111110111100 ,
b1111111110111100 L
b10111100 8
b10111100 K
1>
1F
1M
1T
b1111111110000100 !
b1111111110000100 3
b1111111111100001 1
b1111111111100001 :
b1111111111100001 C
b1111111111100001 J
b1111111111100001 Q
b1111111110100011 /
b1111111110100011 a
b0 5
b0 `
1G
b111111111111100001 .
b111111111110000100 2
b111111111110000100 X
b111111111110000100 0
b1111111110111100 -
b1111111110111100 E
b10111100 '
b10111100 *
b10111100 D
b10101 (
1$
#310
0$
#315
1U
b1111111110111100 +
b1111111110111100 S
b10111100 9
b10111100 R
b1111111111001110 ,
b1111111111001110 L
b11001110 8
b11001110 K
b1111111110100011 7
b1111111110100011 <
b0 6
b0 ;
b1111111101011000 !
b1111111101011000 3
b1111111110110101 1
b1111111110110101 :
b1111111110110101 C
b1111111110110101 J
b1111111110110101 Q
b111111111110110101 .
b111111111101011000 2
b111111111101011000 X
b111111111101011000 0
b1111111111001110 -
b1111111111001110 E
b11001110 '
b11001110 *
b11001110 D
b10110 (
1$
#320
0$
#325
b1111111111001110 +
b1111111111001110 S
b11001110 9
b11001110 R
b1111111111010101 ,
b1111111111010101 L
b11010101 8
b11010101 K
b1111111101111000 !
b1111111101111000 3
b1111111111010101 1
b1111111111010101 :
b1111111111010101 C
b1111111111010101 J
b1111111111010101 Q
b111111111111010101 .
b111111111101111000 2
b111111111101111000 X
b111111111101111000 0
b1111111111010101 -
b1111111111010101 E
b11010101 '
b11010101 *
b11010101 D
b10111 (
1$
#330
0$
#335
b1111111111010101 +
b1111111111010101 S
b11010101 9
b11010101 R
b1111111111011011 ,
b1111111111011011 L
b11011011 8
b11011011 K
b1111111110001011 !
b1111111110001011 3
b1111111111101000 1
b1111111111101000 :
b1111111111101000 C
b1111111111101000 J
b1111111111101000 Q
b111111111111101000 .
b111111111110001011 2
b111111111110001011 X
b111111111110001011 0
b1111111111011011 -
b1111111111011011 E
b11011011 '
b11011011 *
b11011011 D
b11000 (
1$
#340
0$
#345
0N
b1111111111011011 +
b1111111111011011 S
b11011011 9
b11011011 R
b111110 ,
b111110 L
b111110 8
b111110 K
1>
1F
1M
1T
b1010111 !
b1010111 3
b1111111111111010 1
b1111111111111010 :
b1111111111111010 C
b1111111111111010 J
b1111111111111010 Q
b1011101 /
b1011101 a
b11 5
b11 `
0G
b111111111111111010 .
b1010111 2
b1010111 X
b1010111 0
b111110 -
b111110 E
b111110 '
b111110 *
b111110 D
b11001 (
1$
#350
0$
#355
0U
1N
1=
b111110 +
b111110 S
b111110 9
b111110 R
b1111111111001110 ,
b1111111111001110 L
b11001110 8
b11001110 K
b1011101 7
b1011101 <
b11 6
b11 ;
1>
1F
1M
1T
b1111111111011010 !
b1111111111011010 3
b1111111111111001 1
b1111111111111001 :
b1111111111111001 C
b1111111111111001 J
b1111111111111001 Q
b1111111111100001 /
b1111111111100001 a
b1 5
b1 `
1G
b111111111111111001 .
b111111111111011010 2
b111111111111011010 X
b111111111111011010 0
b1111111111001110 -
b1111111111001110 E
b11001110 '
b11001110 *
b11001110 D
b11010 (
1$
#360
0$
#365
0=
1U
0N
b1111111111100001 7
b1111111111100001 <
b1 6
b1 ;
b1111111111001110 +
b1111111111001110 S
b11001110 9
b11001110 R
b110 ,
b110 L
b110 8
b110 K
1>
1F
1M
1T
b1111111111011010 !
b1111111111011010 3
b1111111111111001 1
b1111111111111001 :
b1111111111111001 C
b1111111111111001 J
b1111111111111001 Q
b1111111111100001 /
b1111111111100001 a
b1 5
b1 `
0G
b111111111111111001 .
b111111111111011010 2
b111111111111011010 X
b111111111111011010 0
b110 -
b110 E
b110 '
b110 *
b110 D
b11011 (
1$
#370
0$
#375
0U
b11111 /
b11111 a
b10 5
b10 `
b110 +
b110 S
b110 9
b110 R
b11001 ,
b11001 L
b11001 8
b11001 K
0>
0F
0M
0T
b111000 !
b111000 3
b11001 1
b11001 :
b11001 C
b11001 J
b11001 Q
b11001 .
b111000 2
b111000 X
b111000 0
b11001 -
b11001 E
b11001 '
b11001 *
b11001 D
b11100 (
1$
#380
0$
#385
1=
1N
b11111 7
b11111 <
b10 6
b10 ;
b11001 +
b11001 S
b11001 9
b11001 R
b1111111111000010 ,
b1111111111000010 L
b11000010 8
b11000010 K
1>
1F
1M
1T
b1111111110011101 !
b1111111110011101 3
b1111111111111010 1
b1111111111111010 :
b1111111111111010 C
b1111111111111010 J
b1111111111111010 Q
b1111111110100011 /
b1111111110100011 a
b0 5
b0 `
1G
b111111111111111010 .
b111111111110011101 2
b111111111110011101 X
b111111111110011101 0
b1111111111000010 -
b1111111111000010 E
b11000010 '
b11000010 *
b11000010 D
b11101 (
1$
#390
0$
#395
1U
0N
0=
b1111111111000010 +
b1111111111000010 S
b11000010 9
b11000010 R
b0 ,
b0 L
b0 8
b0 K
b1111111110100011 7
b1111111110100011 <
b0 6
b0 ;
1>
1F
1M
1T
b1111111111000010 !
b1111111111000010 3
b1111111111100001 1
b1111111111100001 :
b1111111111100001 C
b1111111111100001 J
b1111111111100001 Q
b1111111111100001 /
b1111111111100001 a
b1 5
b1 `
0G
b111111111111100001 .
b111111111111000010 2
b111111111111000010 X
b111111111111000010 0
b0 -
b0 E
b0 '
b0 *
b0 D
b11110 (
1$
#400
0$
